vargula/__init__.py
vargula/benchmark.py
vargula/demo.py
vargula/tutorial.py
vargula/usage.py
vargula/vargula.py
vargula-2.0.2.dist-info/licenses/LICENSE
vargula-2.0.2.dist-info/METADATA
vargula-2.0.2.dist-info/WHEEL
vargula-2.0.2.dist-info/entry_points.txt
vargula-2.0.2.dist-info/top_level.txt
vargula-2.0.2.dist-info/RECORD
