Metadata-Version: 2.4
Name: vargula
Version: 2.0.2
Summary: Vargula is a lightweight Python library that makes terminal text styling effortless. With support for colors, backgrounds, text styles, and an intuitive markup format, you can create beautiful CLI applications with just a few lines of code.
Author-email: Sivaprasad Murali <sivaprasad.off@gmail.com>
Maintainer-email: Sivaprasad Murali <sivaprasad.off@gmail.com>
License: MIT
Project-URL: Homepage, https://github.com/Crystallinecore/vargula
Project-URL: Documentation, https://github.com/Crystallinecore/vargula#readme
Project-URL: Source, https://github.com/Crystallinecore/vargula
Project-URL: Tracker, https://github.com/Crystallinecore/vargula/issues
Project-URL: Releases, https://github.com/Crystallinecore/vargula/releases
Keywords: terminal,console,color,style,ansi,text,formatting,markup,theme,cli,tui,rich,colorama,cross-platform,windows,linux,macos
Classifier: Development Status :: 5 - Production/Stable
Classifier: Intended Audience :: Developers
Classifier: Topic :: Software Development :: Libraries :: Python Modules
Classifier: Topic :: Software Development :: User Interfaces
Classifier: Topic :: System :: Shells
Classifier: Topic :: Terminals
Classifier: Topic :: Utilities
Classifier: License :: OSI Approved :: MIT License
Classifier: Operating System :: OS Independent
Classifier: Operating System :: Microsoft :: Windows
Classifier: Operating System :: POSIX :: Linux
Classifier: Operating System :: MacOS
Classifier: Programming Language :: Python :: 3
Classifier: Programming Language :: Python :: 3.7
Classifier: Programming Language :: Python :: 3.8
Classifier: Programming Language :: Python :: 3.9
Classifier: Programming Language :: Python :: 3.10
Classifier: Programming Language :: Python :: 3.11
Classifier: Programming Language :: Python :: 3.12
Classifier: Programming Language :: Python :: 3.13
Classifier: Programming Language :: Python :: Implementation :: CPython
Classifier: Programming Language :: Python :: Implementation :: PyPy
Classifier: Typing :: Typed
Classifier: Environment :: Console
Requires-Python: >=3.7
License-File: LICENSE
Dynamic: license-file
